sum_04640/__init__.py
sum_04640-0.0.1.dist-info/LICENCE.txt
sum_04640-0.0.1.dist-info/METADATA
sum_04640-0.0.1.dist-info/WHEEL
sum_04640-0.0.1.dist-info/top_level.txt
sum_04640-0.0.1.dist-info/RECORD
